calculadora/__init__.py
calculadora/operacoes.py
diego_calculadora_2025-0.1.0.dist-info/licenses/LICENSE
tests/__init__.py
tests/test_operacoes.py
diego_calculadora_2025-0.1.0.dist-info/METADATA
diego_calculadora_2025-0.1.0.dist-info/WHEEL
diego_calculadora_2025-0.1.0.dist-info/top_level.txt
diego_calculadora_2025-0.1.0.dist-info/RECORD
