Metadata-Version: 2.4
Name: diego-calculadora-2025
Version: 0.1.0
Summary: Uma calculadora simples em Python
Home-page: https://github.com/seu_usuario/diego-calculadora-2025
Author: Diego
Author-email: diegoivanmendes@gmail.com
License: MIT
Requires-Python: >=3.6
License-File: LICENSE
Dynamic: author
Dynamic: author-email
Dynamic: description
Dynamic: description-content-type
Dynamic: home-page
Dynamic: license
Dynamic: license-file
Dynamic: requires-python
Dynamic: summary
